terran/__init__.py
terran/apps.py
terran/admin/__init__.py
terran/admin/_filter.py
terran/admin/_format.py
terran/admin/country.py
terran/admin/currency.py
terran/admin/level1area.py
terran/admin/level2area.py
terran/admin/settlement.py
terran/migrations/0001_initial.py
terran/migrations/__init__.py
terran/models/__init__.py
terran/models/_format.py
terran/models/country.py
terran/models/currency.py
terran/models/level1area.py
terran/models/level2area.py
terran/models/settlement.py
django_terran-0.0.2.dist-info/LICENSE
django_terran-0.0.2.dist-info/LICENSES
django_terran-0.0.2.dist-info/METADATA
django_terran-0.0.2.dist-info/WHEEL
django_terran-0.0.2.dist-info/top_level.txt
django_terran-0.0.2.dist-info/RECORD
