Metadata-Version: 2.1
Name: django-terran
Version: 0.0.2
Summary: Internationalization of your sign up, registration form or other data collection
Author-email: Roman <roman@adontz.com>
Project-URL: Homepage, https://github.com/django-terran/django-terran/
Project-URL: Issues, https://github.com/django-terran/django-terran/issues
Classifier: Programming Language :: Python :: 3
Classifier: License :: OSI Approved :: BSD License
Classifier: Operating System :: OS Independent
Requires-Python: >=3.12
License-File: LICENSE
License-File: LICENSES
Requires-Dist: Django
